survey_kit/__init__.py
survey_kit/serializable.py
survey_kit/calibration/__init__.py
survey_kit/calibration/calibration.py
survey_kit/calibration/moment.py
survey_kit/calibration/trim.py
survey_kit/entropy_balance_weighting/__init__.py
survey_kit/entropy_balance_weighting/ebw_penalty.py
survey_kit/entropy_balance_weighting/ebw_routines.py
survey_kit/entropy_balance_weighting/legacy.py
survey_kit/entropy_balance_weighting/shared.py
survey_kit/entropy_balance_weighting/typing.py
survey_kit/imputation/__init__.py
survey_kit/imputation/implicate.py
survey_kit/imputation/impute.py
survey_kit/imputation/parameters.py
survey_kit/imputation/selection.py
survey_kit/imputation/srmi.py
survey_kit/imputation/variable.py
survey_kit/imputation/utilities/draw_from_quantiles.py
survey_kit/imputation/utilities/lasso.py
survey_kit/imputation/utilities/lightgbm_wrapper.py
survey_kit/orchestration/__init__.py
survey_kit/orchestration/call_status.py
survey_kit/orchestration/callers.py
survey_kit/orchestration/config.py
survey_kit/orchestration/dependency_order.py
survey_kit/orchestration/from_decorator.py
survey_kit/orchestration/from_python.py
survey_kit/orchestration/function.py
survey_kit/orchestration/legacy_dependency_ordering.py
survey_kit/orchestration/log.py
survey_kit/orchestration/need_to_run.py
survey_kit/orchestration/path_with_fallbacks.py
survey_kit/orchestration/shared_memory.py
survey_kit/orchestration/tracker.py
survey_kit/orchestration/utilities.py
survey_kit/statistics/__init__.py
survey_kit/statistics/basic_calculations.py
survey_kit/statistics/bootstrap.py
survey_kit/statistics/calculator.py
survey_kit/statistics/comparisons.py
survey_kit/statistics/multiple_imputation.py
survey_kit/statistics/replicates.py
survey_kit/statistics/rounding.py
survey_kit/statistics/statistics.py
survey_kit/tutorials/runner.py
survey_kit/utilities/__init__.py
survey_kit/utilities/compress.py
survey_kit/utilities/dataframe.py
survey_kit/utilities/dataframe_list.py
survey_kit-0.1.2.dist-info/METADATA
survey_kit-0.1.2.dist-info/WHEEL
survey_kit-0.1.2.dist-info/licenses/LICENSE.md
survey_kit-0.1.2.dist-info/RECORD
